pysda/__init__.py
pysda/data.py
pysda/mst.py
pysda/mstResult.py
pysda/tpt.py
pysda/tpt_make_fig.py
pysda/util.py
pysda-0.1.6.dist-info/LICENSE.txt
pysda-0.1.6.dist-info/METADATA
pysda-0.1.6.dist-info/WHEEL
pysda-0.1.6.dist-info/top_level.txt
pysda-0.1.6.dist-info/RECORD
