Metadata-Version: 2.1
Name: pysda
Version: 0.1.6
Summary: A suite for diffusion analysis algorithms.
Home-page: https://bitbucket.org/wcchin/pysda
Author: WenLab: Tzai-Hung Wen (Director), Wei-Chin Benny Chen, Fei-Ying Felix Kuo
Author-email: wenthung@gmail.com
License: LICENSE.txt
Keywords: diffusion model
Platform: UNKNOWN
Classifier: Development Status :: 3 - Alpha
Classifier: Intended Audience :: Science/Research
Classifier: Topic :: Scientific/Engineering :: GIS
Classifier: License :: OSI Approved :: MIT License
Classifier: Programming Language :: Python :: 3.5
Requires-Dist: numpy
Requires-Dist: scipy
Requires-Dist: pandas
Requires-Dist: geopandas
Requires-Dist: shapely
Requires-Dist: descartes
Requires-Dist: matplotlib
Requires-Dist: seaborn
Requires-Dist: datetime
Requires-Dist: python-dateutil
Requires-Dist: imageio
Requires-Dist: tapitas
Requires-Dist: mstdbscan
